pynomo/__init__.py
pynomo/circ_scale.py
pynomo/isopleth.py
pynomo/math_utilities.py
pynomo/nomo_axis.py
pynomo/nomo_axis_func.py
pynomo/nomo_grid.py
pynomo/nomo_grid_box.py
pynomo/nomo_low_level_ex.py
pynomo/nomo_wrapper.py
pynomo/nomograph3.py
pynomo/nomographer.py
PyNomo-0.3.6.dist-info/AUTHORS.txt
PyNomo-0.3.6.dist-info/LICENSE
PyNomo-0.3.6.dist-info/LICENSE.txt
PyNomo-0.3.6.dist-info/METADATA
PyNomo-0.3.6.dist-info/WHEEL
PyNomo-0.3.6.dist-info/top_level.txt
PyNomo-0.3.6.dist-info/RECORD
