Metadata-Version: 2.1
Name: PyNomo
Version: 0.3.6
Summary: PyNomo - Python Nomograms
Home-page: http://pynomo.org/
Download-URL: https://github.com/lefakkomies/pynomo
Author: Leif Roschier
Author-email: leif.roschier@iki.fi
License: GPL
Keywords: nomograph nomogram graphics calculator visualization
Platform: OS Independent
Classifier: Development Status :: 4 - Beta
Classifier: Topic :: Scientific/Engineering :: Visualization
Classifier: Topic :: Multimedia :: Graphics
Classifier: Topic :: Software Development :: Libraries :: Python Modules
Classifier: License :: OSI Approved :: GNU General Public License (GPL)
Classifier: Programming Language :: Python
License-File: LICENSE
License-File: LICENSE.txt
License-File: AUTHORS.txt
